pathlit/__init__.py
pathlit/client.py
pathlit-0.0.4.dist-info/METADATA
pathlit-0.0.4.dist-info/WHEEL
pathlit-0.0.4.dist-info/top_level.txt
pathlit-0.0.4.dist-info/RECORD
