Metadata-Version: 2.1
Name: pathlit
Version: 0.0.4
Summary: PathLit engine Python SDK
Home-page: https://github.com/pathlit/python-sdk-demo
Author: PathLit Developers
Author-email: maintainers@pathlit.io
License: UNKNOWN
Project-URL: Bug Tracker, https://github.com/pathlit/python-sdk-demo/issues
Platform: UNKNOWN
Classifier: Programming Language :: Python :: 3
Classifier: License :: OSI Approved :: MIT License
Classifier: Operating System :: OS Independent
Requires-Python: >=3.6
